svnwrap.py
svnwrap-0.8.2.dist-info/LICENSE.rst
svnwrap-0.8.2.dist-info/METADATA
svnwrap-0.8.2.dist-info/WHEEL
svnwrap-0.8.2.dist-info/entry_points.txt
svnwrap-0.8.2.dist-info/top_level.txt
svnwrap-0.8.2.dist-info/zip-safe
svnwrap-0.8.2.dist-info/RECORD
