Metadata-Version: 2.1
Name: svnwrap
Version: 0.8.2
Summary: Wrapper script for Subversion command-line client
Home-page: https://github.com/drmikehenry/svnwrap
Author: Michael Henry
Author-email: drmikehenry@drmikehenry.com
License: MIT
Keywords: svn subversion wrapper
Platform: UNKNOWN
Classifier: Development Status :: 5 - Production/Stable
Classifier: Topic :: Software Development :: Version Control
Classifier: Environment :: Console
Classifier: License :: OSI Approved :: MIT License
Classifier: Programming Language :: Python :: 2
Classifier: Programming Language :: Python :: 2.7
Classifier: Programming Language :: Python :: 3
Classifier: Programming Language :: Python :: 3.4
Classifier: Programming Language :: Python :: 3.5
Classifier: Programming Language :: Python :: 3.6
Classifier: Programming Language :: Python :: 3.7
Classifier: Programming Language :: Python :: 3.8
Requires-Python: >=2.7,!=3.0.*,!=3.1.*,!=3.2.*,!=3.3.*
Requires-Dist: colorama (==0.4.1) ; python_version < "3.5"
Requires-Dist: colorama (==0.4.3) ; python_version >= "3.5"
Provides-Extra: dev
Requires-Dist: pytest ; extra == 'dev'
Requires-Dist: pytest-cov ; extra == 'dev'
Requires-Dist: flake8 (>=3.3.0) ; extra == 'dev'
Requires-Dist: pep8-naming (>=0.4.1) ; extra == 'dev'
Requires-Dist: flake8-quotes (>=0.8.1) ; extra == 'dev'
Requires-Dist: flake8-import-order (>=0.9.0) ; extra == 'dev'
Requires-Dist: mypy ; (python_version >= "3.5") and extra == 'dev'
